par_yt2text/__init__.py
par_yt2text/__main__.py
par_yt2text/py.typed
par_yt2text-0.2.1.dist-info/METADATA
par_yt2text-0.2.1.dist-info/WHEEL
par_yt2text-0.2.1.dist-info/entry_points.txt
par_yt2text-0.2.1.dist-info/licenses/LICENSE
par_yt2text-0.2.1.dist-info/RECORD
