Metadata-Version: 2.3
Name: par_yt2text
Version: 0.2.1
Summary: Extracts metadata about a video, such as the transcript, duration, and comments, with optional audio transcription using OpenAI Whisper.
Project-URL: Homepage, https://github.com/paulrobello/par_yt2text
Project-URL: Documentation, https://github.com/paulrobello/par_yt2text/blob/main/README.md
Project-URL: Repository, https://github.com/paulrobello/par_yt2text
Project-URL: Issues, https://github.com/paulrobello/par_yt2text/issues
Project-URL: Discussions, https://github.com/paulrobello/par_yt2text/discussions
Project-URL: Wiki, https://github.com/paulrobello/par_yt2text/wiki
Author-email: Paul Robello <probello@gmail.com>
Maintainer-email: Paul Robello <probello@gmail.com>
License: MIT License
Keywords: transcript,youtube
Classifier: Development Status :: 4 - Beta
Classifier: Environment :: Console
Classifier: Intended Audience :: Developers
Classifier: License :: OSI Approved :: MIT License
Classifier: Programming Language :: Python :: 3
Classifier: Programming Language :: Python :: 3.11
Classifier: Programming Language :: Python :: 3.12
Classifier: Topic :: Multimedia :: Sound/Audio
Classifier: Topic :: Multimedia :: Video
Classifier: Topic :: Software Development :: Libraries :: Python Modules
Classifier: Typing :: Typed
Requires-Python: >=3.11
Requires-Dist: google-api-python-client>=2.149.0
Requires-Dist: google-auth-httplib2>=0.2.0
Requires-Dist: google-auth-oauthlib>=1.2.1
Requires-Dist: isodate>=0.7.2
Requires-Dist: openai>=1.52.0
Requires-Dist: python-dotenv>=1.0.1
Requires-Dist: pytube>=15.0.0
Requires-Dist: pytubefix>=8.1.1
Requires-Dist: ruff>=0.7.1
Requires-Dist: youtube-transcript-api>=0.6.2
Provides-Extra: local-whisper
Requires-Dist: openai-whisper; extra == 'local-whisper'
Requires-Dist: torch==2.5.0+cu121; extra == 'local-whisper'
Requires-Dist: torchaudio==2.5.0+cu121; extra == 'local-whisper'
Requires-Dist: torchvision==0.20.0+cu121; extra == 'local-whisper'
